CHANGELOG.md
LICENSE
MANIFEST.in
README.md
setup.cfg
setup.py
django_http_method/__init__.py
django_http_method/apps.py
django_http_method/mixins.py
django_http_method/tests.py
django_http_method/views.py
django_http_method.egg-info/PKG-INFO
django_http_method.egg-info/SOURCES.txt
django_http_method.egg-info/dependency_links.txt
django_http_method.egg-info/requires.txt
django_http_method.egg-info/top_level.txt
django_http_method/templatetags/__init__.py
django_http_method/templatetags/http_method.py